__init__.py
housemate_app/__init__.py
housemate_app/housemate_main.py
housemate_app/my_property/__init__.py
housemate_app/my_property/property.py
housemate_app/my_property/purchase.py
housemate_app/my_property/rental.py
housemate_app/user/__init__.py
housemate_app/user/security.py
housemate_app/user/userlogin.py
housemate_app/user/userprofile.py
housemate-2.5.dist-info/LICENSE.txt
housemate-2.5.dist-info/METADATA
housemate-2.5.dist-info/WHEEL
housemate-2.5.dist-info/top_level.txt
housemate-2.5.dist-info/RECORD
