Metadata-Version: 2.1
Name: housemate
Version: 2.5
Summary: HouseMate shows users different properties to rent or purchase based on their specific needs.
Author-email: Andrew Sarracini <andrewsarracini1@gmail.com>, Craig Adlam <cadlam87@gmail.com>
Project-URL: Homepage, https://github.com/CraigAdlam/housemate
Classifier: Programming Language :: Python :: 3
Classifier: License :: OSI Approved :: MIT License
Classifier: Operating System :: OS Independent
Requires-Python: >=3.6
License-File: LICENSE.txt
